mypy_boto3_builder/__init__.py
mypy_boto3_builder/__main__.py
mypy_boto3_builder/cli_parser.py
mypy_boto3_builder/constants.py
mypy_boto3_builder/debug.py
mypy_boto3_builder/exceptions.py
mypy_boto3_builder/jinja_manager.py
mypy_boto3_builder/logger.py
mypy_boto3_builder/main.py
mypy_boto3_builder/package_data.py
mypy_boto3_builder/py.typed
mypy_boto3_builder/service_name.py
mypy_boto3_builder/type_defs.py
mypy_boto3_builder/boto3_ports/__init__.py
mypy_boto3_builder/boto3_ports/model.py
mypy_boto3_builder/chat/__init__.py
mypy_boto3_builder/chat/chat.py
mypy_boto3_builder/chat/chat_buddy.py
mypy_boto3_builder/chat/choice.py
mypy_boto3_builder/chat/enums.py
mypy_boto3_builder/chat/text_style.py
mypy_boto3_builder/chat/type_defs.py
mypy_boto3_builder/chat/utils.py
mypy_boto3_builder/chat/prompts/__init__.py
mypy_boto3_builder/chat/prompts/base_prompt.py
mypy_boto3_builder/chat/prompts/multiselect_prompt.py
mypy_boto3_builder/chat/prompts/path_prompt.py
mypy_boto3_builder/chat/prompts/select_prompt.py
mypy_boto3_builder/enums/__init__.py
mypy_boto3_builder/enums/output_type.py
mypy_boto3_builder/enums/product.py
mypy_boto3_builder/enums/product_library.py
mypy_boto3_builder/enums/product_type.py
mypy_boto3_builder/enums/service_module_name.py
mypy_boto3_builder/generators/__init__.py
mypy_boto3_builder/generators/aioboto3_generator.py
mypy_boto3_builder/generators/aiobotocore_generator.py
mypy_boto3_builder/generators/base_generator.py
mypy_boto3_builder/generators/boto34_generator.py
mypy_boto3_builder/generators/boto3_generator.py
mypy_boto3_builder/generators/mypy_boto3_generator.py
mypy_boto3_builder/generators/types_boto3_generator.py
mypy_boto3_builder/import_helpers/__init__.py
mypy_boto3_builder/import_helpers/import_helper.py
mypy_boto3_builder/import_helpers/import_parent.py
mypy_boto3_builder/import_helpers/import_record.py
mypy_boto3_builder/import_helpers/import_record_group.py
mypy_boto3_builder/import_helpers/import_string.py
mypy_boto3_builder-8.12.0.dist-info/licenses/LICENSE
mypy_boto3_builder-8.12.0.dist-info/METADATA
mypy_boto3_builder-8.12.0.dist-info/WHEEL
mypy_boto3_builder-8.12.0.dist-info/entry_points.txt
mypy_boto3_builder-8.12.0.dist-info/top_level.txt
mypy_boto3_builder-8.12.0.dist-info/RECORD
