Metadata-Version: 2.4
Name: mypy-boto3-builder
Version: 8.12.0
Summary: Type annotations generator for types-boto3, boto3-stubs, types-aiobotocore, and types-aioboto3.
Author-email: Vlad Emelianov <vlad.emelianov.nz@gmail.com>
License: MIT License
Project-URL: Homepage, https://github.com/youtype/mypy_boto3_builder
Project-URL: Documentation, https://youtype.github.io/mypy_boto3_builder/
Project-URL: Repository, https://github.com/youtype/mypy_boto3_builder
Project-URL: Changelog, https://github.com/youtype/mypy_boto3_builder/releases
Project-URL: Issues, https://github.com/youtype/mypy_boto3_builder/issues
Keywords: boto3,type-annotations,pyright,mypy,boto3-stubs
Classifier: Development Status :: 5 - Production/Stable
Classifier: Environment :: Console
Classifier: License :: OSI Approved :: MIT License
Classifier: Natural Language :: English
Classifier: Operating System :: OS Independent
Classifier: Programming Language :: Python :: 3
Classifier: Programming Language :: Python :: 3.12
Classifier: Programming Language :: Python :: 3.13
Classifier: Programming Language :: Python :: 3.14
Classifier: Programming Language :: Python :: 3 :: Only
Classifier: Programming Language :: Python :: Implementation :: CPython
Classifier: Typing :: Typed
Classifier: Topic :: Software Development :: Libraries :: Python Modules
Requires-Python: >=3.12
License-File: LICENSE
Requires-Dist: jinja2
Requires-Dist: loguru
Requires-Dist: mdformat
Requires-Dist: packaging
Requires-Dist: boto3
Requires-Dist: botocore
Requires-Dist: requests
Requires-Dist: ruff
Requires-Dist: setuptools
Requires-Dist: prompt-toolkit
Requires-Dist: questionary>=2.0.1
Provides-Extra: build
Requires-Dist: setuptools; extra == "build"
Provides-Extra: check
Requires-Dist: boto3-stubs; extra == "check"
Requires-Dist: types-aiobotocore; extra == "check"
Requires-Dist: types-aioboto3; extra == "check"
Dynamic: license-file
